.git_archival.txt
.gitattributes
.gitignore
.pre-commit-config.yaml
LICENSE
MANIFEST.in
README.md
environment.yml
mkdocs.yml
pyproject.toml
.github/FUNDING.yml
.github/actions/conda-setup/action.yml
.github/workflows/gh-pages.yml
.github/workflows/lint.yml
.github/workflows/pypi_upload.yml
.github/workflows/tests.yaml
docs/index.md
docs/api/impact_t.md
docs/api/z/api.md
docs/api/z/input.md
docs/api/z/output.md
docs/assets/plot.png
docs/assets/zpz.png
docs/examples/autophase_example.ipynb
docs/examples/basic_impact_examples.ipynb
docs/examples/bmad_interface.ipynb
docs/examples/compare_covariance.ipynb
docs/examples/distgen_example.ipynb
docs/examples/fieldmap_reconstruction.ipynb
docs/examples/functional_impact_run.ipynb
docs/examples/input_parsing_example.ipynb
docs/examples/movie_example.ipynb
docs/examples/output_parsing_example.ipynb
docs/examples/parallel_run_example.ipynb
docs/examples/plotting_example.ipynb
docs/examples/point_to_point_spacecharge.ipynb
docs/examples/bmad_to_impact/corrector_coil/bmad_to_impact.ipynb
docs/examples/bmad_to_impact/corrector_coil/compare.ipynb
docs/examples/bmad_to_impact/corrector_coil/lat.bmad
docs/examples/devel/devel_solrf_fieldmaps.ipynb
docs/examples/elements/3d_field.ipynb
docs/examples/elements/apex_gun.ipynb
docs/examples/elements/awa_flatbeam.ipynb
docs/examples/elements/corrector_coil.ipynb
docs/examples/elements/dipole.ipynb
docs/examples/elements/drift.ipynb
docs/examples/elements/quadrupole.ipynb
docs/examples/elements/solenoid.ipynb
docs/examples/elements/tesla_9cell_cavity.ipynb
docs/examples/elements/traveling_wave_cavity.ipynb
docs/examples/elements/wakefield.ipynb
docs/examples/templates/3dfield/1T1.T7
docs/examples/templates/3dfield/ImpactT.in
docs/examples/templates/3dfield/rfdata102
docs/examples/templates/apex_gun/2019_11_04_135614reg_out.txt
docs/examples/templates/apex_gun/ImpactT.in
docs/examples/templates/apex_gun/apex-gun-lume-impact.png
docs/examples/templates/apex_gun/apex_gun.ipynb
lume_impact.egg-info/PKG-INFO
lume_impact.egg-info/SOURCES.txt
lume_impact.egg-info/dependency_links.txt
lume_impact.egg-info/requires.txt
lume_impact.egg-info/top_level.txt
