Metadata-Version: 2.4
Name: lume-impact
Version: 0.10.1
Summary: Tools for using Impact-T and Impact-Z in LUME
Author: Christopher Mayes
License:                                  Apache License
Project-URL: Homepage, https://github.com/ChristopherMayes/lume-impact
Classifier: Development Status :: 4 - Beta
Classifier: Natural Language :: English
Classifier: Programming Language :: Python :: 3
Classifier: Topic :: Scientific/Engineering
Requires-Python: >=3.9
License-File: LICENSE
Provides-Extra: dev
Requires-Dist: pytest; extra == "dev"
Requires-Dist: pytest-cov; extra == "dev"
Provides-Extra: doc
Requires-Dist: mkdocs==1.5.2; extra == "doc"
Requires-Dist: mkdocs-jupyter==0.24.6; extra == "doc"
Requires-Dist: mkdocs-macros-plugin; extra == "doc"
Requires-Dist: mkdocs-material; extra == "doc"
Requires-Dist: mkdocstrings; extra == "doc"
Requires-Dist: mkdocstrings-python; extra == "doc"
Dynamic: license-file
